[
  {
    "ContainingType": "BookLibary.Api.Controllers.UserController",
    "Method": "Login",
    "RelativePath": "api/User",
    "HttpMethod": "POST",
    "IsController": true,
    "Order": 0,
    "Parameters": [
      {
        "Name": "model",
        "Type": "BookLibary.Api.Dtos.LoginDto",
        "IsRequired": true
      }
    ],
    "ReturnTypes": []
  },
  {
    "ContainingType": "BookLibary.Api.Controllers.UserController",
    "Method": "GetByName",
    "RelativePath": "api/User/{name}",
    "HttpMethod": "GET",
    "IsController": true,
    "Order": 0,
    "Parameters": [
      {
        "Name": "name",
        "Type": "System.String",
        "IsRequired": true
      }
    ],
    "ReturnTypes": []
  }
]